LICENSE
MANIFEST.in
README.rst
buildout.cfg
develop.cfg
pyproject.toml
requirements.txt
setup.py
version.txt
bob/__init__.py
bob.io.audio.egg-info/PKG-INFO
bob.io.audio.egg-info/SOURCES.txt
bob.io.audio.egg-info/dependency_links.txt
bob.io.audio.egg-info/not-zip-safe
bob.io.audio.egg-info/requires.txt
bob.io.audio.egg-info/top_level.txt
bob/io/__init__.py
bob/io/audio/__init__.py
bob/io/audio/bobskin.cpp
bob/io/audio/bobskin.h
bob/io/audio/file.cpp
bob/io/audio/file.h
bob/io/audio/main.cpp
bob/io/audio/main.h
bob/io/audio/reader.cpp
bob/io/audio/test.py
bob/io/audio/version.cpp
bob/io/audio/writer.cpp
bob/io/audio/cpp/reader.cpp
bob/io/audio/cpp/reader.h
bob/io/audio/cpp/utils.cpp
bob/io/audio/cpp/utils.h
bob/io/audio/cpp/writer.cpp
bob/io/audio/cpp/writer.h
bob/io/audio/data/sample1.sph
bob/io/audio/data/sample1.wav
bob/io/audio/data/sample3.wav
bob/io/audio/data/sample3_matlab.hdf5
bob/io/audio/data/sample4.wav
bob/io/audio/data/timit-sa1.sph
bob/io/audio/data/timit-sa1.wav
bob/io/audio/data/timit-sa2.sph
bob/io/audio/data/timit-sa2.wav
doc/conf.py
doc/index.rst
doc/links.rst
doc/py_api.rst