Metadata-Version: 2.1
Name: bob.io.audio
Version: 2.0.15
Summary: Audio I/O support for Bob
Home-page: http://gitlab.idiap.ch/bob/bob.io.audio
Author: Andre Anjos
Author-email: andre.anjos@idiap.ch
License: BSD
Platform: UNKNOWN
Classifier: Framework :: Bob
Classifier: Development Status :: 4 - Beta
Classifier: Intended Audience :: Developers
Classifier: License :: OSI Approved :: BSD License
Classifier: Natural Language :: English
Classifier: Programming Language :: Python
Classifier: Programming Language :: Python :: 3
Classifier: Topic :: Software Development :: Libraries :: Python Modules
Classifier: Environment :: Plugins
License-File: LICENSE
